logging_extension/__init__.py
logging_extension/filters.py
logging_extension/formatters.py
logging_extension/handlers.py
logging_extension-0.4.0.dist-info/LICENSE
logging_extension-0.4.0.dist-info/METADATA
logging_extension-0.4.0.dist-info/WHEEL
logging_extension-0.4.0.dist-info/top_level.txt
logging_extension-0.4.0.dist-info/RECORD
