Metadata-Version: 2.1
Name: logging-extension
Version: 0.4.0
Summary: Extensions for the original logging module
Author-email: Nikita Bulavinov <jktujgxtu@gmail.com>
License: MIT License
Project-URL: Homepage, https://github.com/jktujg/logging-extension
Project-URL: Bug Tracker, https://github.com/jktujg/logging-extension/issues
Keywords: logging,formatter,handler,filter,JSON,thread
Classifier: License :: OSI Approved :: MIT License
Classifier: Operating System :: OS Independent
Classifier: Programming Language :: Python :: 3.11
Classifier: Programming Language :: Python :: 3.12
Requires-Python: >=3.11
License-File: LICENSE
